PyTrinamicTools/__init__.py
PyTrinamicTools/version.py
PyTrinamicTools/helpers/Microsteps.py
PyTrinamicTools-0.1.0.data/scripts/MicrostepCalculator.py
PyTrinamicTools-0.1.0.dist-info/LICENSE
PyTrinamicTools-0.1.0.dist-info/METADATA
PyTrinamicTools-0.1.0.dist-info/WHEEL
PyTrinamicTools-0.1.0.dist-info/top_level.txt
PyTrinamicTools-0.1.0.dist-info/RECORD
